hf_torrent/__init__.py
hf_torrent/download.py
hf_torrent/main.py
hf_torrent/utils.py
hf_torrent-0.0.1_2401021918.data/scripts/hf-torrent
hf_torrent-0.0.1.post2401021918.dist-info/METADATA
hf_torrent-0.0.1.post2401021918.dist-info/WHEEL
hf_torrent-0.0.1.post2401021918.dist-info/top_level.txt
hf_torrent-0.0.1.post2401021918.dist-info/zip-safe
hf_torrent-0.0.1.post2401021918.dist-info/RECORD
