Metadata-Version: 2.1
Name: hf-torrent
Version: 0.0.1-2401021918
Summary: A tool to download HuggingFace models via BitTorrent.
Home-page: https://github.com/Lyken17/hf-torrent/
Author: Ligeng Zhu
Author-email: lykensyu+github@gmail.com
License: MIT
Platform: UNKNOWN
Classifier: Programming Language :: Python :: 3
Requires-Dist: bencodepy
Requires-Dist: aria2p[tui]
Requires-Dist: fire
